moat/lib/run/__init__.py
moat_lib_run-0.1.1.dist-info/licenses/LICENSE.txt
moat_lib_run-0.1.1.dist-info/METADATA
moat_lib_run-0.1.1.dist-info/WHEEL
moat_lib_run-0.1.1.dist-info/top_level.txt
moat_lib_run-0.1.1.dist-info/RECORD
