Metadata-Version: 2.4
Name: moat-lib-run
Version: 0.1.1
Summary: Main command entry point infrastructure for MoaT applications
Maintainer-email: Matthias Urlichs <matthias@urlichs.de>
Project-URL: homepage, https://m-o-a-t.org
Project-URL: repository, https://github.com/M-o-a-T/moat
Keywords: MoaT
Classifier: Development Status :: 4 - Beta
Classifier: Framework :: AnyIO
Classifier: Framework :: Trio
Classifier: Framework :: AsyncIO
Classifier: Programming Language :: Python :: 3
Classifier: Intended Audience :: Developers
Requires-Python: >=3.8
License-File: LICENSE.txt
Requires-Dist: anyio~=4.0
Requires-Dist: moat-util~=0.61.1
Requires-Dist: asyncclick~=8.0
Requires-Dist: simpleeval~=1.0
Requires-Dist: moat-lib-config~=0.1.0
Requires-Dist: moat-lib-proxy~=0.1.0
Dynamic: license-file
